{
  "GroupPT20": {
    "title": "Physician (Group)",
    "type": "object",
    "anyOf": [
      {
        "type": "object",
        "properties": {
          "provideHealthyStepsServices": {
            "type": "boolean",
            "enum": [
              true
            ]
          },
          "healthyStepsConfirmationLetter": {
            "$ref": "../../common/common-schema-ref.json#/FileAttachment"
          },
          "provideCenteringPregnancyCare": {
            "type": "boolean",
            "enum": [
              true
            ]
          },
          "centeringPregnancyApprovalLetter": {
            "$ref": "../../common/common-schema-ref.json#/FileAttachment"
          },
          "isPainManagementClinic": {
            "type": "boolean",
            "enum": [
              true
            ]
          },
          "painManagementClinicCredentials": {
            "type": "array",
            "title": "Attach credentials for Pain Management Clinic",
            "items": {
              "$ref": "../../common/common-schema-ref.json#/FileAttachment"
            },
            "minItems": 1
          },
          "SBHCSponsoringAgency": {
            "type": "boolean",
            "enum": [
              true
            ]
          },
          "SBHCSponsoringAgencyInfo": {
            "type": "object",
            "properties": {
              "billingProviderNPI": {
                "$ref": "../../common/common-pattern-ref.json#/ProviderNPI"
              },
              "billingProviderTaxID": {
                "$ref": "../../common/common-pattern-ref.json#/TaxIdNumber"
              },
              "billingProviderMA": {
                "$ref": "../../common/common-pattern-ref.json#/MANumber"
              },
              "SBHCName": {
                "type": "string",
                "pattern": "^[A-Za-z0-9 @#&,.\\-'/]+$",
                "description": "Name of the SBHC."
              },
              "streetAddressLine1": {
                "$ref": "../../common/common-pattern-ref.json#/PrimaryStreetAddress"
              },
              "streetAddressLine2": {
                "$ref": "../../common/common-pattern-ref.json#/SecondaryStreetAddress"
              },
              "city": {
                "$ref": "../../common/common-pattern-ref.json#/City"
              },
              "state": {
                "$ref": "../../common/common-pattern-ref.json#/StateCode"
              },
              "zipCode": {
                "$ref": "../../common/common-pattern-ref.json#/ZipCode"
              },
              "locationChange": {
                "type": "boolean",
                "description": "Select if this is a location change for an existing SBHC."
              },
              "SBHCApprovalDocument": {
                "$ref": "../../common/common-schema-ref.json#/FileAttachment"
              }
            },
            "additionalProperties": false
          }
        },
        "additionalProperties": false
      },
      {
        "type": "object",
        "properties": {
          "provideHealthyStepsServices": {
            "type": "boolean",
            "enum": [
              false
            ]
          },
          "provideCenteringPregnancyCare": {
            "type": "boolean",
            "enum": [
              false
            ]
          },
          "isPainManagementClinic": {
            "type": "boolean",
            "enum": [
              false
            ]
          },
          "SBHCSponsoringAgency": {
            "type": "boolean",
            "enum": [
              false
            ]
          }
        },
        "additionalProperties": false
      },
      {
        "type": "object",
        "properties": {
          "provideHealthyStepsServices": {
            "type": "boolean",
            "enum": [
              true
            ]
          },
          "healthyStepsConfirmationLetter": {
            "$ref": "../../common/common-schema-ref.json#/FileAttachment"
          },
          "provideCenteringPregnancyCare": {
            "type": "boolean",
            "enum": [
              true
            ]
          },
          "centeringPregnancyApprovalLetter": {
            "$ref": "../../common/common-schema-ref.json#/FileAttachment"
          },
          "isPainManagementClinic": {
            "type": "boolean",
            "enum": [
              true
            ]
          },
          "painManagementClinicCredentials": {
            "type": "array",
            "title": "Attach credentials for Pain Management Clinic",
            "items": {
              "$ref": "../../common/common-schema-ref.json#/FileAttachment"
            },
            "minItems": 1
          },
          "SBHCSponsoringAgency": {
            "type": "boolean",
            "enum": [
              false
            ]
          }
        },
        "additionalProperties": false
      },
      {
        "type": "object",
        "properties": {
          "provideHealthyStepsServices": {
            "type": "boolean",
            "enum": [
              true
            ]
          },
          "healthyStepsConfirmationLetter": {
            "$ref": "../../common/common-schema-ref.json#/FileAttachment"
          },
          "provideCenteringPregnancyCare": {
            "type": "boolean",
            "enum": [
              true
            ]
          },
          "centeringPregnancyApprovalLetter": {
            "$ref": "../../common/common-schema-ref.json#/FileAttachment"
          },
          "isPainManagementClinic": {
            "type": "boolean",
            "enum": [
              false
            ]
          },
          "SBHCSponsoringAgency": {
            "type": "boolean",
            "enum": [
              true
            ]
          },
          "SBHCSponsoringAgencyInfo": {
            "type": "object",
            "properties": {
              "billingProviderNPI": {
                "$ref": "../../common/common-pattern-ref.json#/ProviderNPI"
              },
              "billingProviderTaxID": {
                "$ref": "../../common/common-pattern-ref.json#/TaxIdNumber"
              },
              "billingProviderMA": {
                "$ref": "../../common/common-pattern-ref.json#/MANumber"
              },
              "SBHCName": {
                "type": "string",
                "pattern": "^[A-Za-z0-9 @#&,.\\-'/]+$",
                "description": "Name of the SBHC."
              },
              "streetAddressLine1": {
                "$ref": "../../common/common-pattern-ref.json#/PrimaryStreetAddress"
              },
              "streetAddressLine2": {
                "$ref": "../../common/common-pattern-ref.json#/SecondaryStreetAddress"
              },
              "city": {
                "$ref": "../../common/common-pattern-ref.json#/City"
              },
              "state": {
                "$ref": "../../common/common-pattern-ref.json#/StateCode"
              },
              "zipCode": {
                "$ref": "../../common/common-pattern-ref.json#/ZipCode"
              },
              "locationChange": {
                "type": "boolean",
                "description": "Select if this is a location change for an existing SBHC."
              },
              "SBHCApprovalDocument": {
                "$ref": "../../common/common-schema-ref.json#/FileAttachment"
              }
            },
            "additionalProperties": false
          }
        },
        "additionalProperties": false
      },
      {
        "type": "object",
        "properties": {
          "provideHealthyStepsServices": {
            "type": "boolean",
            "enum": [
              true
            ]
          },
          "healthyStepsConfirmationLetter": {
            "$ref": "../../common/common-schema-ref.json#/FileAttachment"
          },
          "provideCenteringPregnancyCare": {
            "type": "boolean",
            "enum": [
              true
            ]
          },
          "centeringPregnancyApprovalLetter": {
            "$ref": "../../common/common-schema-ref.json#/FileAttachment"
          },
          "isPainManagementClinic": {
            "type": "boolean",
            "enum": [
              false
            ]
          },
          "SBHCSponsoringAgency": {
            "type": "boolean",
            "enum": [
              false
            ]
          }
        },
        "additionalProperties": false
      },
      {
        "type": "object",
        "properties": {
          "provideHealthyStepsServices": {
            "type": "boolean",
            "enum": [
              true
            ]
          },
          "healthyStepsConfirmationLetter": {
            "$ref": "../../common/common-schema-ref.json#/FileAttachment"
          },
          "provideCenteringPregnancyCare": {
            "type": "boolean",
            "enum": [
              false
            ]
          },
          "isPainManagementClinic": {
            "type": "boolean",
            "enum": [
              true
            ]
          },
          "painManagementClinicCredentials": {
            "type": "array",
            "title": "Attach credentials for Pain Management Clinic",
            "items": {
              "$ref": "../../common/common-schema-ref.json#/FileAttachment"
            },
            "minItems": 1
          },
          "SBHCSponsoringAgency": {
            "type": "boolean",
            "enum": [
              true
            ]
          },
          "SBHCSponsoringAgencyInfo": {
            "type": "object",
            "properties": {
              "billingProviderNPI": {
                "$ref": "../../common/common-pattern-ref.json#/ProviderNPI"
              },
              "billingProviderTaxID": {
                "$ref": "../../common/common-pattern-ref.json#/TaxIdNumber"
              },
              "billingProviderMA": {
                "$ref": "../../common/common-pattern-ref.json#/MANumber"
              },
              "SBHCName": {
                "type": "string",
                "pattern": "^[A-Za-z0-9 @#&,.\\-'/]+$",
                "description": "Name of the SBHC."
              },
              "streetAddressLine1": {
                "$ref": "../../common/common-pattern-ref.json#/PrimaryStreetAddress"
              },
              "streetAddressLine2": {
                "$ref": "../../common/common-pattern-ref.json#/SecondaryStreetAddress"
              },
              "city": {
                "$ref": "../../common/common-pattern-ref.json#/City"
              },
              "state": {
                "$ref": "../../common/common-pattern-ref.json#/StateCode"
              },
              "zipCode": {
                "$ref": "../../common/common-pattern-ref.json#/ZipCode"
              },
              "locationChange": {
                "type": "boolean",
                "description": "Select if this is a location change for an existing SBHC."
              },
              "SBHCApprovalDocument": {
                "$ref": "../../common/common-schema-ref.json#/FileAttachment"
              }
            },
            "additionalProperties": false
          }
        },
        "additionalProperties": false
      },
      {
        "type": "object",
        "properties": {
          "provideHealthyStepsServices": {
            "type": "boolean",
            "enum": [
              true
            ]
          },
          "healthyStepsConfirmationLetter": {
            "$ref": "../../common/common-schema-ref.json#/FileAttachment"
          },
          "provideCenteringPregnancyCare": {
            "type": "boolean",
            "enum": [
              false
            ]
          },
          "isPainManagementClinic": {
            "type": "boolean",
            "enum": [
              true
            ]
          },
          "painManagementClinicCredentials": {
            "type": "array",
            "title": "Attach credentials for Pain Management Clinic",
            "items": {
              "$ref": "../../common/common-schema-ref.json#/FileAttachment"
            },
            "minItems": 1
          },
          "SBHCSponsoringAgency": {
            "type": "boolean",
            "enum": [
              false
            ]
          }
        },
        "additionalProperties": false
      },
      {
        "type": "object",
        "properties": {
          "provideHealthyStepsServices": {
            "type": "boolean",
            "enum": [
              true
            ]
          },
          "healthyStepsConfirmationLetter": {
            "$ref": "../../common/common-schema-ref.json#/FileAttachment"
          },
          "provideCenteringPregnancyCare": {
            "type": "boolean",
            "enum": [
              false
            ]
          },
          "isPainManagementClinic": {
            "type": "boolean",
            "enum": [
              false
            ]
          },
          "SBHCSponsoringAgency": {
            "type": "boolean",
            "enum": [
              true
            ]
          },
          "SBHCSponsoringAgencyInfo": {
            "type": "object",
            "properties": {
              "billingProviderNPI": {
                "$ref": "../../common/common-pattern-ref.json#/ProviderNPI"
              },
              "billingProviderTaxID": {
                "$ref": "../../common/common-pattern-ref.json#/TaxIdNumber"
              },
              "billingProviderMA": {
                "$ref": "../../common/common-pattern-ref.json#/MANumber"
              },
              "SBHCName": {
                "type": "string",
                "pattern": "^[A-Za-z0-9 @#&,.\\-'/]+$",
                "description": "Name of the SBHC."
              },
              "streetAddressLine1": {
                "$ref": "../../common/common-pattern-ref.json#/PrimaryStreetAddress"
              },
              "streetAddressLine2": {
                "$ref": "../../common/common-pattern-ref.json#/SecondaryStreetAddress"
              },
              "city": {
                "$ref": "../../common/common-pattern-ref.json#/City"
              },
              "state": {
                "$ref": "../../common/common-pattern-ref.json#/StateCode"
              },
              "zipCode": {
                "$ref": "../../common/common-pattern-ref.json#/ZipCode"
              },
              "locationChange": {
                "type": "boolean",
                "description": "Select if this is a location change for an existing SBHC."
              },
              "SBHCApprovalDocument": {
                "$ref": "../../common/common-schema-ref.json#/FileAttachment"
              }
            },
            "additionalProperties": false
          }
        },
        "additionalProperties": false
      },
      {
        "type": "object",
        "properties": {
          "provideHealthyStepsServices": {
            "type": "boolean",
            "enum": [
              true
            ]
          },
          "healthyStepsConfirmationLetter": {
            "$ref": "../../common/common-schema-ref.json#/FileAttachment"
          },
          "provideCenteringPregnancyCare": {
            "type": "boolean",
            "enum": [
              false
            ]
          },
          "isPainManagementClinic": {
            "type": "boolean",
            "enum": [
              false
            ]
          },
          "SBHCSponsoringAgency": {
            "type": "boolean",
            "enum": [
              false
            ]
          }
        },
        "additionalProperties": false
      },
      {
        "type": "object",
        "properties": {
          "provideHealthyStepsServices": {
            "type": "boolean",
            "enum": [
              false
            ]
          },
          "provideCenteringPregnancyCare": {
            "type": "boolean",
            "enum": [
              true
            ]
          },
          "centeringPregnancyApprovalLetter": {
            "$ref": "../../common/common-schema-ref.json#/FileAttachment"
          },
          "isPainManagementClinic": {
            "type": "boolean",
            "enum": [
              true
            ]
          },
          "painManagementClinicCredentials": {
            "type": "array",
            "title": "Attach credentials for Pain Management Clinic",
            "items": {
              "$ref": "../../common/common-schema-ref.json#/FileAttachment"
            },
            "minItems": 1
          },
          "SBHCSponsoringAgency": {
            "type": "boolean",
            "enum": [
              true
            ]
          },
          "SBHCSponsoringAgencyInfo": {
            "type": "object",
            "properties": {
              "billingProviderNPI": {
                "$ref": "../../common/common-pattern-ref.json#/ProviderNPI"
              },
              "billingProviderTaxID": {
                "$ref": "../../common/common-pattern-ref.json#/TaxIdNumber"
              },
              "billingProviderMA": {
                "$ref": "../../common/common-pattern-ref.json#/MANumber"
              },
              "SBHCName": {
                "type": "string",
                "pattern": "^[A-Za-z0-9 @#&,.\\-'/]+$",
                "description": "Name of the SBHC."
              },
              "streetAddressLine1": {
                "$ref": "../../common/common-pattern-ref.json#/PrimaryStreetAddress"
              },
              "streetAddressLine2": {
                "$ref": "../../common/common-pattern-ref.json#/SecondaryStreetAddress"
              },
              "city": {
                "$ref": "../../common/common-pattern-ref.json#/City"
              },
              "state": {
                "$ref": "../../common/common-pattern-ref.json#/StateCode"
              },
              "zipCode": {
                "$ref": "../../common/common-pattern-ref.json#/ZipCode"
              },
              "locationChange": {
                "type": "boolean",
                "description": "Select if this is a location change for an existing SBHC."
              },
              "SBHCApprovalDocument": {
                "$ref": "../../common/common-schema-ref.json#/FileAttachment"
              }
            },
            "additionalProperties": false
          }
        },
        "additionalProperties": false
      },
      {
        "type": "object",
        "properties": {
          "provideHealthyStepsServices": {
            "type": "boolean",
            "enum": [
              false
            ]
          },
          "provideCenteringPregnancyCare": {
            "type": "boolean",
            "enum": [
              true
            ]
          },
          "centeringPregnancyApprovalLetter": {
            "$ref": "../../common/common-schema-ref.json#/FileAttachment"
          },
          "isPainManagementClinic": {
            "type": "boolean",
            "enum": [
              true
            ]
          },
          "painManagementClinicCredentials": {
            "type": "array",
            "title": "Attach credentials for Pain Management Clinic",
            "items": {
              "$ref": "../../common/common-schema-ref.json#/FileAttachment"
            },
            "minItems": 1
          },
          "SBHCSponsoringAgency": {
            "type": "boolean",
            "enum": [
              false
            ]
          }
        },
        "additionalProperties": false
      },
      {
        "type": "object",
        "properties": {
          "provideHealthyStepsServices": {
            "type": "boolean",
            "enum": [
              false
            ]
          },
          "provideCenteringPregnancyCare": {
            "type": "boolean",
            "enum": [
              true
            ]
          },
          "centeringPregnancyApprovalLetter": {
            "$ref": "../../common/common-schema-ref.json#/FileAttachment"
          },
          "isPainManagementClinic": {
            "type": "boolean",
            "enum": [
              false
            ]
          },
          "SBHCSponsoringAgency": {
            "type": "boolean",
            "enum": [
              true
            ]
          },
          "SBHCSponsoringAgencyInfo": {
            "type": "object",
            "properties": {
              "billingProviderNPI": {
                "$ref": "../../common/common-pattern-ref.json#/ProviderNPI"
              },
              "billingProviderTaxID": {
                "$ref": "../../common/common-pattern-ref.json#/TaxIdNumber"
              },
              "billingProviderMA": {
                "$ref": "../../common/common-pattern-ref.json#/MANumber"
              },
              "SBHCName": {
                "type": "string",
                "pattern": "^[A-Za-z0-9 @#&,.\\-'/]+$",
                "description": "Name of the SBHC."
              },
              "streetAddressLine1": {
                "$ref": "../../common/common-pattern-ref.json#/PrimaryStreetAddress"
              },
              "streetAddressLine2": {
                "$ref": "../../common/common-pattern-ref.json#/SecondaryStreetAddress"
              },
              "city": {
                "$ref": "../../common/common-pattern-ref.json#/City"
              },
              "state": {
                "$ref": "../../common/common-pattern-ref.json#/StateCode"
              },
              "zipCode": {
                "$ref": "../../common/common-pattern-ref.json#/ZipCode"
              },
              "locationChange": {
                "type": "boolean",
                "description": "Select if this is a location change for an existing SBHC."
              },
              "SBHCApprovalDocument": {
                "$ref": "../../common/common-schema-ref.json#/FileAttachment"
              }
            },
            "additionalProperties": false
          }
        },
        "additionalProperties": false
      },
      {
        "type": "object",
        "properties": {
          "provideHealthyStepsServices": {
            "type": "boolean",
            "enum": [
              false
            ]
          },
          "provideCenteringPregnancyCare": {
            "type": "boolean",
            "enum": [
              true
            ]
          },
          "centeringPregnancyApprovalLetter": {
            "$ref": "../../common/common-schema-ref.json#/FileAttachment"
          },
          "isPainManagementClinic": {
            "type": "boolean",
            "enum": [
              false
            ]
          },
          "SBHCSponsoringAgency": {
            "type": "boolean",
            "enum": [
              false
            ]
          }
        },
        "additionalProperties": false
      },
      {
        "type": "object",
        "properties": {
          "provideHealthyStepsServices": {
            "type": "boolean",
            "enum": [
              false
            ]
          },
          "provideCenteringPregnancyCare": {
            "type": "boolean",
            "enum": [
              false
            ]
          },
          "isPainManagementClinic": {
            "type": "boolean",
            "enum": [
              true
            ]
          },
          "painManagementClinicCredentials": {
            "type": "array",
            "title": "Attach credentials for Pain Management Clinic",
            "items": {
              "$ref": "../../common/common-schema-ref.json#/FileAttachment"
            },
            "minItems": 1
          },
          "SBHCSponsoringAgency": {
            "type": "boolean",
            "enum": [
              true
            ]
          },
          "SBHCSponsoringAgencyInfo": {
            "type": "object",
            "properties": {
              "billingProviderNPI": {
                "$ref": "../../common/common-pattern-ref.json#/ProviderNPI"
              },
              "billingProviderTaxID": {
                "$ref": "../../common/common-pattern-ref.json#/TaxIdNumber"
              },
              "billingProviderMA": {
                "$ref": "../../common/common-pattern-ref.json#/MANumber"
              },
              "SBHCName": {
                "type": "string",
                "pattern": "^[A-Za-z0-9 @#&,.\\-'/]+$",
                "description": "Name of the SBHC."
              },
              "streetAddressLine1": {
                "$ref": "../../common/common-pattern-ref.json#/PrimaryStreetAddress"
              },
              "streetAddressLine2": {
                "$ref": "../../common/common-pattern-ref.json#/SecondaryStreetAddress"
              },
              "city": {
                "$ref": "../../common/common-pattern-ref.json#/City"
              },
              "state": {
                "$ref": "../../common/common-pattern-ref.json#/StateCode"
              },
              "zipCode": {
                "$ref": "../../common/common-pattern-ref.json#/ZipCode"
              },
              "locationChange": {
                "type": "boolean",
                "description": "Select if this is a location change for an existing SBHC."
              },
              "SBHCApprovalDocument": {
                "$ref": "../../common/common-schema-ref.json#/FileAttachment"
              }
            },
            "additionalProperties": false
          }
        },
        "additionalProperties": false
      },
      {
        "type": "object",
        "properties": {
          "provideHealthyStepsServices": {
            "type": "boolean",
            "enum": [
              false
            ]
          },
          "provideCenteringPregnancyCare": {
            "type": "boolean",
            "enum": [
              false
            ]
          },
          "isPainManagementClinic": {
            "type": "boolean",
            "enum": [
              true
            ]
          },
          "painManagementClinicCredentials": {
            "type": "array",
            "title": "Attach credentials for Pain Management Clinic",
            "items": {
              "$ref": "../../common/common-schema-ref.json#/FileAttachment"
            },
            "minItems": 1
          },
          "SBHCSponsoringAgency": {
            "type": "boolean",
            "enum": [
              false
            ]
          }
        },
        "additionalProperties": false
      },
      {
        "type": "object",
        "properties": {
          "provideHealthyStepsServices": {
            "type": "boolean",
            "enum": [
              false
            ]
          },
          "provideCenteringPregnancyCare": {
            "type": "boolean",
            "enum": [
              false
            ]
          },
          "isPainManagementClinic": {
            "type": "boolean",
            "enum": [
              false
            ]
          },
          "SBHCSponsoringAgency": {
            "type": "boolean",
            "enum": [
              true
            ]
          },
          "SBHCSponsoringAgencyInfo": {
            "type": "object",
            "properties": {
              "billingProviderNPI": {
                "$ref": "../../common/common-pattern-ref.json#/ProviderNPI"
              },
              "billingProviderTaxID": {
                "$ref": "../../common/common-pattern-ref.json#/TaxIdNumber"
              },
              "billingProviderMA": {
                "$ref": "../../common/common-pattern-ref.json#/MANumber"
              },
              "SBHCName": {
                "type": "string",
                "pattern": "^[A-Za-z0-9 @#&,.\\-'/]+$",
                "description": "Name of the SBHC."
              },
              "streetAddressLine1": {
                "$ref": "../../common/common-pattern-ref.json#/PrimaryStreetAddress"
              },
              "streetAddressLine2": {
                "$ref": "../../common/common-pattern-ref.json#/SecondaryStreetAddress"
              },
              "city": {
                "$ref": "../../common/common-pattern-ref.json#/City"
              },
              "state": {
                "$ref": "../../common/common-pattern-ref.json#/StateCode"
              },
              "zipCode": {
                "$ref": "../../common/common-pattern-ref.json#/ZipCode"
              },
              "locationChange": {
                "type": "boolean",
                "description": "Select if this is a location change for an existing SBHC."
              },
              "SBHCApprovalDocument": {
                "$ref": "../../common/common-schema-ref.json#/FileAttachment"
              }
            },
            "additionalProperties": false
          }
        },
        "additionalProperties": false
      }
    ]
  }
}